MANIFEST.in
changelog.txt
setup.py
ISAPIWSGIHelper.egg-info/PKG-INFO
ISAPIWSGIHelper.egg-info/SOURCES.txt
ISAPIWSGIHelper.egg-info/dependency_links.txt
ISAPIWSGIHelper.egg-info/not-zip-safe
ISAPIWSGIHelper.egg-info/requires.txt
ISAPIWSGIHelper.egg-info/top_level.txt
iwhelper/__init__.py
iwhelper/command.py
iwhelper/utils.py
iwhelper/templates/_loader.py.tpl
iwhelper/templates/appinit.py.tpl