Metadata-Version: 1.0
Name: ISAPIWSGIHelper
Version: 0.1.1
Summary: utilities to help bootstrap deployment of WSGI applications using isapi-wsgi
Home-page: http://bitbucket.org/rsyring/isapi-wsgi-helper/
Author: Randy Syring
Author-email: rsyring@gmail.com
License: BSD
Platform: UNKNOWN
Classifier: Development Status :: 4 - Beta
Classifier: Intended Audience :: Developers
Classifier: Intended Audience :: System Administrators
Classifier: License :: OSI Approved :: BSD License
